{
  "name": "零基础保姆级节点搭建教学",
  "children": [
    {
      "name": "准备工作",
      "children": [
        {
          "name": "VPS购买 (搬瓦工 CN2 GIA)",
          "children": [
            {
              "name": "选择洛杉矶机房"
            },
            {
              "name": "使用优惠码"
            },
            {
              "name": "支付宝结算"
            }
          ]
        },
        {
          "name": "域名注册 (Namesilo)",
          "children": [
            {
              "name": "搜索便宜后缀"
            },
            {
              "name": "解析IP到VPS"
            }
          ]
        }
      ]
    },
    {
      "name": "VPS环境配置",
      "children": [
        {
          "name": "重装系统为 Ubuntu 22.04"
        },
        {
          "name": "使用 FinalShell 连接 SSH"
        },
        {
          "name": "开启 BBR 加速"
        },
        {
          "name": "更新操作系统软件源"
        }
      ]
    },
    {
      "name": "核心组件安装",
      "children": [
        {
          "name": "x-ui 面板安装",
          "children": [
            {
              "name": "设置用户名密码"
            },
            {
              "name": "设置访问端口"
            }
          ]
        },
        {
          "name": "SSL证书申请",
          "children": [
            {
              "name": "安装 acme.sh"
            },
            {
              "name": "自动申请并安装证书"
            }
          ]
        }
      ]
    },
    {
      "name": "安全与伪装配置",
      "children": [
        {
          "name": "寻找伪装网站 (私人网盘)"
        },
        {
          "name": "Nginx 反向代理配置",
          "children": [
            {
              "name": "配置 443 端口转发"
            },
            {
              "name": "隐藏 x-ui 管理路径"
            },
            {
              "name": "配置分流路径"
            }
          ]
        }
      ]
    },
    {
      "name": "节点创建与连接",
      "children": [
        {
          "name": "x-ui 节点设置",
          "children": [
            {
              "name": "协议: VMess/VLESS"
            },
            {
              "name": "传输方式: WebSocket (WS)"
            },
            {
              "name": "监听地址: 127.0.0.1"
            }
          ]
        },
        {
          "name": "客户端参数修改",
          "children": [
            {
              "name": "地址改为域名"
            },
            {
              "name": "端口改为 443"
            },
            {
              "name": "开启 TLS"
            }
          ]
        }
      ]
    },
    {
      "name": "多用户合租方案",
      "children": [
        {
          "name": "WS 路径分流"
        },
        {
          "name": "限制总流量与到期时间"
        },
        {
          "name": "单端口多用户共享 443"
        }
      ]
    }
  ]
}