{
  "name": "巴菲特2026年投资建议",
  "children": [
    {
      "name": "市场四大预警信号",
      "children": [
        {
          "name": "债务杠杆激增",
          "children": [
            {
              "name": "借钱炒股现象普遍"
            },
            {
              "name": "生活成本推动私人债务"
            },
            {
              "name": "市场估值人为虚高"
            }
          ]
        },
        {
          "name": "集中度风险",
          "children": [
            {
              "name": "少数科技巨头主导指数"
            },
            {
              "name": "市盈率远超历史均值"
            },
            {
              "name": "AI炒作推高股价"
            }
          ]
        },
        {
          "name": "巴菲特指标过热",
          "children": [
            {
              "name": "股市总市值/GDP"
            },
            {
              "name": "偏离历史均值两倍标准差"
            },
            {
              "name": "历史上预示市场调整"
            }
          ]
        },
        {
          "name": "散户投机行为",
          "children": [
            {
              "name": "日内交易与期权激增"
            },
            {
              "name": "追求短期利润而非长期持有"
            },
            {
              "name": "过度频繁的交易活动"
            }
          ]
        }
      ]
    },
    {
      "name": "巴菲特四大投资准则",
      "children": [
        {
          "name": "视股票为业务",
          "children": [
            {
              "name": "关注基本面而非价格波动"
            },
            {
              "name": "防御性行业（如必需品）"
            },
            {
              "name": "正确对待“市场先生”的报价"
            }
          ]
        },
        {
          "name": "坚守能力圈",
          "children": [
            {
              "name": "明确知识边界"
            },
            {
              "name": "不盲目追随科技趋势"
            },
            {
              "name": "区分新技术与盈利能力"
            }
          ]
        },
        {
          "name": "预留安全边际",
          "children": [
            {
              "name": "价值与价格之间的缓冲"
            },
            {
              "name": "针对高风险资产加大边际"
            },
            {
              "name": "为长期持有抵御短期波动"
            }
          ]
        },
        {
          "name": "减少交易频率",
          "children": [
            {
              "name": "“打孔卡”理论（一生仅买20只股）"
            },
            {
              "name": "避免过度活跃导致的损失"
            },
            {
              "name": "买入并长期忘却的策略"
            }
          ]
        }
      ]
    },
    {
      "name": "理性投资者心态",
      "children": [
        {
          "name": "克服情绪化波动"
        },
        {
          "name": "专注事实与理由"
        },
        {
          "name": "通过复利实现增长"
        }
      ]
    }
  ]
}